{
    "files": [
        {
            "contentLength": 32,
            "contentType": "application/octet-stream",
            "lastModifiedTime": 1714517451.506944,
            "name": "neoforge-20.6.9-beta-changelog.txt.asc.md5",
            "type": "FILE"
        },
        {
            "contentLength": 40,
            "contentType": "application/octet-stream",
            "lastModifiedTime": 1714517451.226944,
            "name": "neoforge-20.6.9-beta-changelog.txt.asc.sha1",
            "type": "FILE"
        },
        {
            "contentLength": 64,
            "contentType": "application/octet-stream",
            "lastModifiedTime": 1714517451.734944,
            "name": "neoforge-20.6.9-beta-changelog.txt.asc.sha256",
            "type": "FILE"
        },
        {
            "contentLength": 128,
            "contentType": "application/octet-stream",
            "lastModifiedTime": 1714517452.038943,
            "name": "neoforge-20.6.9-beta-changelog.txt.asc.sha512",
            "type": "FILE"
        },
        {
            "contentLength": 215,
            "contentType": "application/octet-stream",
            "lastModifiedTime": 1714517451.002944,
            "name": "neoforge-20.6.9-beta-changelog.txt.asc",
            "type": "FILE"
        },
        {
            "contentLength": 32,
            "contentType": "application/octet-stream",
            "lastModifiedTime": 1714517452.606943,
            "name": "neoforge-20.6.9-beta-changelog.txt.md5",
            "type": "FILE"
        },
        {
            "contentLength": 40,
            "contentType": "application/octet-stream",
            "lastModifiedTime": 1714517452.378943,
            "name": "neoforge-20.6.9-beta-changelog.txt.sha1",
            "type": "FILE"
        },
        {
            "contentLength": 64,
            "contentType": "application/octet-stream",
            "lastModifiedTime": 1714517452.834943,
            "name": "neoforge-20.6.9-beta-changelog.txt.sha256",
            "type": "FILE"
        },
        {
            "contentLength": 128,
            "contentType": "application/octet-stream",
            "lastModifiedTime": 1714517453.066943,
            "name": "neoforge-20.6.9-beta-changelog.txt.sha512",
            "type": "FILE"
        },
        {
            "contentLength": 691,
            "contentType": "text/plain",
            "lastModifiedTime": 1714517452.146943,
            "name": "neoforge-20.6.9-beta-changelog.txt",
            "type": "FILE"
        },
        {
            "contentLength": 32,
            "contentType": "application/octet-stream",
            "lastModifiedTime": 1714517455.146942,
            "name": "neoforge-20.6.9-beta-installer.jar.asc.md5",
            "type": "FILE"
        },
        {
            "contentLength": 40,
            "contentType": "application/octet-stream",
            "lastModifiedTime": 1714517454.914942,
            "name": "neoforge-20.6.9-beta-installer.jar.asc.sha1",
            "type": "FILE"
        },
        {
            "contentLength": 64,
            "contentType": "application/octet-stream",
            "lastModifiedTime": 1714517455.382941,
            "name": "neoforge-20.6.9-beta-installer.jar.asc.sha256",
            "type": "FILE"
        },
        {
            "contentLength": 128,
            "contentType": "application/octet-stream",
            "lastModifiedTime": 1714517455.602941,
            "name": "neoforge-20.6.9-beta-installer.jar.asc.sha512",
            "type": "FILE"
        },
        {
            "contentLength": 215,
            "contentType": "application/octet-stream",
            "lastModifiedTime": 1714517454.650942,
            "name": "neoforge-20.6.9-beta-installer.jar.asc",
            "type": "FILE"
        },
        {
            "contentLength": 32,
            "contentType": "application/octet-stream",
            "lastModifiedTime": 1719920439.271358,
            "name": "neoforge-20.6.9-beta-installer.jar.md5",
            "type": "FILE"
        },
        {
            "contentLength": 40,
            "contentType": "application/octet-stream",
            "lastModifiedTime": 1719920438.591358,
            "name": "neoforge-20.6.9-beta-installer.jar.sha1",
            "type": "FILE"
        },
        {
            "contentLength": 64,
            "contentType": "application/octet-stream",
            "lastModifiedTime": 1719920440.155359,
            "name": "neoforge-20.6.9-beta-installer.jar.sha256",
            "type": "FILE"
        },
        {
            "contentLength": 128,
            "contentType": "application/octet-stream",
            "lastModifiedTime": 1719920441.263359,
            "name": "neoforge-20.6.9-beta-installer.jar.sha512",
            "type": "FILE"
        },
        {
            "contentLength": 6470223,
            "contentType": "application/java-archive",
            "lastModifiedTime": 1719912346.45606,
            "name": "neoforge-20.6.9-beta-installer.jar",
            "type": "FILE"
        },
        {
            "contentLength": 16,
            "contentType": "application/octet-stream",
            "lastModifiedTime": 1719912371.224064,
            "name": "neoforge-20.6.9-beta-installer.md5",
            "type": "FILE"
        },
        {
            "contentLength": 20,
            "contentType": "application/octet-stream",
            "lastModifiedTime": 1719912350.512061,
            "name": "neoforge-20.6.9-beta-installer.sha1",
            "type": "FILE"
        },
        {
            "contentLength": 32,
            "contentType": "application/octet-stream",
            "lastModifiedTime": 1719912361.924063,
            "name": "neoforge-20.6.9-beta-installer.sha256",
            "type": "FILE"
        },
        {
            "contentLength": 64,
            "contentType": "application/octet-stream",
            "lastModifiedTime": 1719912355.952062,
            "name": "neoforge-20.6.9-beta-installer.sha512",
            "type": "FILE"
        },
        {
            "contentLength": 32,
            "contentType": "application/octet-stream",
            "lastModifiedTime": 1714517440.03495,
            "name": "neoforge-20.6.9-beta.pom.asc.md5",
            "type": "FILE"
        },
        {
            "contentLength": 40,
            "contentType": "application/octet-stream",
            "lastModifiedTime": 1714517439.81495,
            "name": "neoforge-20.6.9-beta.pom.asc.sha1",
            "type": "FILE"
        },
        {
            "contentLength": 64,
            "contentType": "application/octet-stream",
            "lastModifiedTime": 1714517440.26295,
            "name": "neoforge-20.6.9-beta.pom.asc.sha256",
            "type": "FILE"
        },
        {
            "contentLength": 128,
            "contentType": "application/octet-stream",
            "lastModifiedTime": 1714517440.49095,
            "name": "neoforge-20.6.9-beta.pom.asc.sha512",
            "type": "FILE"
        },
        {
            "contentLength": 215,
            "contentType": "application/octet-stream",
            "lastModifiedTime": 1714517439.586951,
            "name": "neoforge-20.6.9-beta.pom.asc",
            "type": "FILE"
        },
        {
            "contentLength": 32,
            "contentType": "application/octet-stream",
            "lastModifiedTime": 1714517438.354951,
            "name": "neoforge-20.6.9-beta.pom.md5",
            "type": "FILE"
        },
        {
            "contentLength": 40,
            "contentType": "application/octet-stream",
            "lastModifiedTime": 1714517437.946951,
            "name": "neoforge-20.6.9-beta.pom.sha1",
            "type": "FILE"
        },
        {
            "contentLength": 64,
            "contentType": "application/octet-stream",
            "lastModifiedTime": 1714517438.766951,
            "name": "neoforge-20.6.9-beta.pom.sha256",
            "type": "FILE"
        },
        {
            "contentLength": 128,
            "contentType": "application/octet-stream",
            "lastModifiedTime": 1714517439.178951,
            "name": "neoforge-20.6.9-beta.pom.sha512",
            "type": "FILE"
        },
        {
            "contentLength": 17617,
            "contentType": "application/xml",
            "lastModifiedTime": 1714517437.510952,
            "name": "neoforge-20.6.9-beta.pom",
            "type": "FILE"
        },
        {
            "contentLength": 32,
            "contentType": "application/octet-stream",
            "lastModifiedTime": 1714517446.226947,
            "name": "neoforge-20.6.9-beta-sources.jar.asc.md5",
            "type": "FILE"
        },
        {
            "contentLength": 40,
            "contentType": "application/octet-stream",
            "lastModifiedTime": 1714517445.990947,
            "name": "neoforge-20.6.9-beta-sources.jar.asc.sha1",
            "type": "FILE"
        },
        {
            "contentLength": 64,
            "contentType": "application/octet-stream",
            "lastModifiedTime": 1714517446.458947,
            "name": "neoforge-20.6.9-beta-sources.jar.asc.sha256",
            "type": "FILE"
        },
        {
            "contentLength": 128,
            "contentType": "application/octet-stream",
            "lastModifiedTime": 1714517446.730946,
            "name": "neoforge-20.6.9-beta-sources.jar.asc.sha512",
            "type": "FILE"
        },
        {
            "contentLength": 215,
            "contentType": "application/octet-stream",
            "lastModifiedTime": 1714517445.766947,
            "name": "neoforge-20.6.9-beta-sources.jar.asc",
            "type": "FILE"
        },
        {
            "contentLength": 32,
            "contentType": "application/octet-stream",
            "lastModifiedTime": 1714517442.250949,
            "name": "neoforge-20.6.9-beta-sources.jar.md5",
            "type": "FILE"
        },
        {
            "contentLength": 40,
            "contentType": "application/octet-stream",
            "lastModifiedTime": 1714517442.014949,
            "name": "neoforge-20.6.9-beta-sources.jar.sha1",
            "type": "FILE"
        },
        {
            "contentLength": 64,
            "contentType": "application/octet-stream",
            "lastModifiedTime": 1714517442.682949,
            "name": "neoforge-20.6.9-beta-sources.jar.sha256",
            "type": "FILE"
        },
        {
            "contentLength": 128,
            "contentType": "application/octet-stream",
            "lastModifiedTime": 1714517443.102948,
            "name": "neoforge-20.6.9-beta-sources.jar.sha512",
            "type": "FILE"
        },
        {
            "contentLength": 1538061,
            "contentType": "application/java-archive",
            "lastModifiedTime": 1714517441.594949,
            "name": "neoforge-20.6.9-beta-sources.jar",
            "type": "FILE"
        },
        {
            "contentLength": 32,
            "contentType": "application/octet-stream",
            "lastModifiedTime": 1714517450.326944,
            "name": "neoforge-20.6.9-beta-universal.jar.asc.md5",
            "type": "FILE"
        },
        {
            "contentLength": 40,
            "contentType": "application/octet-stream",
            "lastModifiedTime": 1714517450.106944,
            "name": "neoforge-20.6.9-beta-universal.jar.asc.sha1",
            "type": "FILE"
        },
        {
            "contentLength": 64,
            "contentType": "application/octet-stream",
            "lastModifiedTime": 1714517450.566944,
            "name": "neoforge-20.6.9-beta-universal.jar.asc.sha256",
            "type": "FILE"
        },
        {
            "contentLength": 128,
            "contentType": "application/octet-stream",
            "lastModifiedTime": 1714517450.786944,
            "name": "neoforge-20.6.9-beta-universal.jar.asc.sha512",
            "type": "FILE"
        },
        {
            "contentLength": 215,
            "contentType": "application/octet-stream",
            "lastModifiedTime": 1714517449.866945,
            "name": "neoforge-20.6.9-beta-universal.jar.asc",
            "type": "FILE"
        },
        {
            "contentLength": 32,
            "contentType": "application/octet-stream",
            "lastModifiedTime": 1714517444.878947,
            "name": "neoforge-20.6.9-beta-universal.jar.md5",
            "type": "FILE"
        },
        {
            "contentLength": 40,
            "contentType": "application/octet-stream",
            "lastModifiedTime": 1714517444.462948,
            "name": "neoforge-20.6.9-beta-universal.jar.sha1",
            "type": "FILE"
        },
        {
            "contentLength": 64,
            "contentType": "application/octet-stream",
            "lastModifiedTime": 1714517445.098947,
            "name": "neoforge-20.6.9-beta-universal.jar.sha256",
            "type": "FILE"
        },
        {
            "contentLength": 128,
            "contentType": "application/octet-stream",
            "lastModifiedTime": 1714517445.530947,
            "name": "neoforge-20.6.9-beta-universal.jar.sha512",
            "type": "FILE"
        },
        {
            "contentLength": 2636814,
            "contentType": "application/java-archive",
            "lastModifiedTime": 1714517444.034948,
            "name": "neoforge-20.6.9-beta-universal.jar",
            "type": "FILE"
        },
        {
            "contentLength": 32,
            "contentType": "application/octet-stream",
            "lastModifiedTime": 1714517453.762942,
            "name": "neoforge-20.6.9-beta-userdev.jar.asc.md5",
            "type": "FILE"
        },
        {
            "contentLength": 40,
            "contentType": "application/octet-stream",
            "lastModifiedTime": 1714517453.530943,
            "name": "neoforge-20.6.9-beta-userdev.jar.asc.sha1",
            "type": "FILE"
        },
        {
            "contentLength": 64,
            "contentType": "application/octet-stream",
            "lastModifiedTime": 1714517454.002942,
            "name": "neoforge-20.6.9-beta-userdev.jar.asc.sha256",
            "type": "FILE"
        },
        {
            "contentLength": 128,
            "contentType": "application/octet-stream",
            "lastModifiedTime": 1714517454.230942,
            "name": "neoforge-20.6.9-beta-userdev.jar.asc.sha512",
            "type": "FILE"
        },
        {
            "contentLength": 215,
            "contentType": "application/octet-stream",
            "lastModifiedTime": 1714517453.298943,
            "name": "neoforge-20.6.9-beta-userdev.jar.asc",
            "type": "FILE"
        },
        {
            "contentLength": 32,
            "contentType": "application/octet-stream",
            "lastModifiedTime": 1714517457.66294,
            "name": "neoforge-20.6.9-beta-userdev.jar.md5",
            "type": "FILE"
        },
        {
            "contentLength": 40,
            "contentType": "application/octet-stream",
            "lastModifiedTime": 1714517457.24294,
            "name": "neoforge-20.6.9-beta-userdev.jar.sha1",
            "type": "FILE"
        },
        {
            "contentLength": 64,
            "contentType": "application/octet-stream",
            "lastModifiedTime": 1714517457.89894,
            "name": "neoforge-20.6.9-beta-userdev.jar.sha256",
            "type": "FILE"
        },
        {
            "contentLength": 128,
            "contentType": "application/octet-stream",
            "lastModifiedTime": 1714517458.31894,
            "name": "neoforge-20.6.9-beta-userdev.jar.sha512",
            "type": "FILE"
        },
        {
            "contentLength": 3684217,
            "contentType": "application/java-archive",
            "lastModifiedTime": 1714517456.810941,
            "name": "neoforge-20.6.9-beta-userdev.jar",
            "type": "FILE"
        }
    ],
    "name": "20.6.9-beta",
    "type": "DIRECTORY"
}